Workbook

Sheet Расчёт
A1: Расчёт экономического эффекта — три сценария
A2: Все ячейки — формулы от листа «Допущения». Суммы в рублях.
A4: Показатель | B4: Ед. | C4: Как считается | D4: Консерват. | E4: База | F4: Оптимист.
A5: Затраты на создание (разово)
A6: ФОТ на создание | B6: ₽ | C6: оценка автора | D6: =Допущения!D12 -> 500000 | E6: =Допущения!E12 -> 500000 | F6: =Допущения!F12 -> 500000
A7: Прочие разовые | B7: ₽ | C7: из допущений | D7: =Допущения!D13 -> 0 | E7: =Допущения!E13 -> 0 | F7: =Допущения!F13 -> 0
A8: ИТОГО затраты на создание | B8: ₽ | C8: сумма | D8: =SUM(D6:D7) -> 500000 | E8: =SUM(E6:E7) -> 500000 | F8: =SUM(F6:F7) -> 500000
A9: Затраты на эксплуатацию (в год)
A10: Сопровождение и развитие | B10: ₽/год | C10: ФОТ сопровождения | D10: =Допущения!D15 -> 1500000 | E10: =Допущения!E15 -> 1500000 | F10: =Допущения!F15 -> 1500000
A11: Серверы | B11: ₽/год | C11: из допущений | D11: =Допущения!D16 -> 800000 | E11: =Допущения!E16 -> 800000 | F11: =Допущения!F16 -> 800000
A12: ИИ и облачные модели | B12: ₽/год | C12: из допущений | D12: =Допущения!D17 -> 700000 | E12: =Допущения!E17 -> 700000 | F12: =Допущения!F17 -> 700000
A13: ИТОГО эксплуатация | B13: ₽/год | C13: сумма | D13: =SUM(D10:D12) -> 3000000 | E13: =SUM(E10:E12) -> 3000000 | F13: =SUM(F10:F12) -> 3000000
A14: Эффект в год при полном освоении
A15: Людей ручного учёта, которых не нужно нанимать | B15: чел. | C15: объекты / объектов на человека | D15: =Допущения!D22/Допущения!D19 -> 33.333333 | E15: =Допущения!E22/Допущения!E19 -> 33.333333 | F15: =Допущения!F22/Допущения!F19 -> 33.333333
A16: A. Не нужны люди для ручного учёта (ФОТ) | B16: ₽/год | C16: люди × ФОТ человека | D16: =D15*Допущения!D20 -> 60000000 | E16: =E15*Допущения!E20 -> 60000000 | F16: =F15*Допущения!F20 -> 60000000
A17: B. Меньше простоев и срывов поставки | B17: ₽/год | C17: объекты × срывы × дни × цена дня × доля | D17: =Допущения!D22*Допущения!D23*Допущения!D24*Допущения!D25*Допущения!D26 -> 35000000 | E17: =Допущения!E22*Допущения!E23*Допущения!E24*Допущения!E25*Допущения!E26 -> 140000000 | F17: =Допущения!F22*Допущения!F23*Допущения!F24*Допущения!F25*Допущения!F26 -> 630000000
A18: C. Меньше ошибок и переделок | B18: ₽/год | C18: объекты × изделия × доля ошибок × цена × доля устранения | D18: =Допущения!D22*Допущения!D28*Допущения!D29*Допущения!D30*Допущения!D31 -> 5437500 | E18: =Допущения!E22*Допущения!E28*Допущения!E29*Допущения!E30*Допущения!E31 -> 29000000 | F18: =Допущения!F22*Допущения!F28*Допущения!F29*Допущения!F30*Допущения!F31 -> 1.218e+08
A19: D. Деньги и сроки (ПП): стоимость финансирования | B19: ₽/год | C19: объём × доля × дни / 365 × ставка | D19: =Допущения!D33*Допущения!D34*Допущения!D35/365*Допущения!D9 -> 47945.205 | E19: =Допущения!E33*Допущения!E34*Допущения!E35/365*Допущения!E9 -> 438356.16 | F19: =Допущения!F33*Допущения!F34*Допущения!F35/365*Допущения!F9 -> 2219178.1
A20: ИТОГО эффект в год | B20: ₽/год | C20: A + B + C + D | D20: =D16+D17+D18+D19 -> 1.0048545e+08 | E20: =E16+E17+E18+E19 -> 2.2943836e+08 | F20: =F16+F17+F18+F19 -> 8.1401918e+08
A21: Чистый эффект в год (эффект − эксплуатация) | B21: ₽/год | D21: =D20-D13 -> 97485445 | E21: =E20-E13 -> 2.2643836e+08 | F21: =F20-F13 -> 8.1101918e+08
A22: Денежный поток по годам
A23: Год 0: создание | B23: ₽ | C23: −затраты на создание | D23: =-D8 -> -500000 | E23: =-E8 -> -500000 | F23: =-F8 -> -500000
A24: Год 1 | B24: ₽ | C24: эффект × доля освоения − эксплуатация | D24: =D20*Допущения!D7-D13 -> 37194178 | E24: =E20*Допущения!E7-E13 -> 1.1171918e+08 | F24: =F20*Допущения!F7-F13 -> 5.6681342e+08
A25: Год 2 | B25: ₽ | C25: эффект − эксплуатация | D25: =D21 -> 97485445 | E25: =E21 -> 2.2643836e+08 | F25: =F21 -> 8.1101918e+08
A26: Год 3 | B26: ₽ | C26: эффект − эксплуатация | D26: =D21 -> 97485445 | E26: =E21 -> 2.2643836e+08 | F26: =F21 -> 8.1101918e+08
A27: Показатели эффективности (3 года)
A28: Накопленный чистый эффект за 3 года | B28: ₽ | C28: сумма потоков 0–3 | D28: =SUM(D23:D26) -> 2.3166507e+08 | E28: =SUM(E23:E26) -> 5.6409589e+08 | F28: =SUM(F23:F26) -> 2.1883518e+09
A29: NPV | B29: ₽ | C29: потоки, дисконтированные по ставке | D29: =D23+D24/(1+Допущения!D8)+D25/(1+Допущения!D8)^2+D26/(1+Допущения!D8)^3 -> 1.5460856e+08 | E29: =E23+E24/(1+Допущения!E8)+E25/(1+Допущения!E8)^2+E26/(1+Допущения!E8)^3 -> 4.0915969e+08 | F29: =F23+F24/(1+Допущения!F8)+F25/(1+Допущения!F8)^2+F26/(1+Допущения!F8)^3 -> 1.6681725e+09
A30: ROI за 3 года | B30: % | C30: накопленный эффект / затраты на создание | D30: =IF(D8=0,0,D28/D8) -> 463.33014 | E30: =IF(E8=0,0,E28/E8) -> 1128.1918 | F30: =IF(F8=0,0,F28/F8) -> 4376.7036
A31: Срок окупаемости | B31: мес. | C31: по накопленному потоку; >36 — не окупается за горизонт | D31: =IF(D24>=D8,D8/D24*12,IF(D24+D25>=D8,12+(D8-D24)/D25*12,IF(D24+D25+D26>=D8,24+(D8-D24-D25)/D26*12,">36"))) -> 0.16131557 | E31: =IF(E24>=E8,E8/E24*12,IF(E24+E25>=E8,12+(E8-E24)/E25*12,IF(E24+E25+E26>=E8,24+(E8-E24-E25)/E26*12,">36"))) -> 0.053706088 | F31: =IF(F24>=F8,F8/F24*12,IF(F24+F25>=F8,12+(F8-F24)/F25*12,IF(F24+F25+F26>=F8,24+(F8-F24-F25)/F26*12,">36"))) -> 0.010585494
A32: Доля эффекта A (ФОТ ручного учёта) | B32: % | C32: A / итого эффект | D32: =IF(D20=0,0,D16/D20) -> 0.5971014 | E32: =IF(E20=0,0,E16/E20) -> 0.26150815 | F32: =IF(F20=0,0,F16/F20) -> 0.073708337
A33: Безубыточность: сколько простоя нужно предотвратить
A34: Дней простоя в год, предотвращённых в сценарии | B34: дн./год | C34: объекты × срывы × дни × доля | D34: =Допущения!D22*Допущения!D23*Допущения!D24*Допущения!D26 -> 5 | E34: =Допущения!E22*Допущения!E23*Допущения!E24*Допущения!E26 -> 20 | F34: =Допущения!F22*Допущения!F23*Допущения!F24*Допущения!F26 -> 90
A35: Окупить эксплуатацию (без эффекта A, C, D) | B35: дн./год | C35: эксплуатация / цена дня простоя | D35: =D13/Допущения!D25 -> 0.42857143 | E35: =E13/Допущения!E25 -> 0.42857143 | F35: =F13/Допущения!F25 -> 0.42857143
A36: Окупить создание | B36: дн. | C36: затраты на создание / цена дня простоя | D36: =D8/Допущения!D25 -> 0.071428571 | E36: =E8/Допущения!E25 -> 0.071428571 | F36: =F8/Допущения!F25 -> 0.071428571
A38: A — ФОТ ставок, которые пришлось бы посадить на ручной учёт и отчёты без сервиса (альтернатива: Excel/почта). B, C, D — вероятностные: зависят от доли предотвращённых событий, которую нужно подтверждать замерами на пилотных объектах.
A39: При цене дня простоя 7 млн ₽ главный аргумент — безубыточность: блок внизу показывает, сколько дней простоя в год достаточно предотвратить, чтобы окупить создание и эксплуатацию.
A40: Эффект масштабируется числом объектов (A, B, C): сегодня модель изделий загружена на 2 объекта из 110 активных, поэтому расчёт принимает 100 объектов по решению автора.
A41: Затраты на создание — условный ФОТ 500 тыс. ₽ (оценка автора: работа велась вечерами без доплаты; история git — 74 дня — приведена справочно).

Sheet Допущения
A1: Допущения к расчёту экономического эффекта ЖБИ-трекера
A2: Как пользоваться: жёлтые ячейки — ГИПОТЕЗЫ «на глаз», их нужно заменить вашими цифрами (тогда расчёт станет обоснованным). Синий текст без заливки — факт из проекта (источник в комментарии). Три столбца — сценарии: консервативный (эффект меньше, затраты больше), базовый, оптимистичный.
A4: Параметр | B4: Ед. | C4: Тип | D4: Консерват. | E4: База | F4: Оптимист. | G4: Источник / комментарий
A5: 0. Общие
A6: Горизонт расчёта | B6: лет | C6: факт | D6: 3 | E6: 3 | F6: 3 | G6: Условность: 3 года эксплуатации после создания
A7: Доля эффекта в 1-й год (освоение) | B7: % | C7: гипотеза | D7: 0.4 | E7: 0.5 | F7: 0.7 | G7: Пользователи осваивают сервис постепенно; со 2-го года — 100%
A8: Ставка дисконтирования | B8: % | C8: гипотеза | D8: 0.2 | E8: 0.16 | F8: 0.14 | G8: Стоимость денег в компании; заменить на корпоративную
A9: Стоимость финансирования (кредитная ставка) | B9: %/год | C9: гипотеза | D9: 0.14 | E9: 0.16 | F9: 0.18 | G9: Нужна для эффекта «деньги и сроки»
A10: 1. Затраты на создание (разовые)
A11: Справочно: активных дней разработки | B11: дн. | C11: факт | D11: 74 | E11: 74 | F11: 74 | G11: git: 74 дня с коммитами, 16.07–23.10.2026 (1236 коммитов, ~303 тыс. строк кода, ~49 тыс. строк документации); в расчёт не входит — работа велась вечерами и в свободное время
A12: ФОТ на создание сервиса | B12: ₽ | C12: факт | D12: 500000 | E12: 500000 | F12: 500000 | G12: Оценка автора: работа без доплаты, условно 500 000 ₽
A13: Прочие разовые затраты (железо, лицензии, внедрение) | B13: ₽ | C13: гипотеза | D13: 0 | E13: 0 | F13: 0 | G13: Принято 0: используется существующая инфраструктура; если закупалось — внести
A14: 2. Затраты на эксплуатацию (в год)
A15: ФОТ сопровождения и развития | B15: ₽/год | C15: факт | D15: 1500000 | E15: 1500000 | F15: 1500000 | G15: Решение автора: эксплуатация на 100 объектах 3 млн ₽/год в сумме; разбивка по статьям — оценка
A16: Серверы и инфраструктура | B16: ₽/год | C16: факт | D16: 800000 | E16: 800000 | F16: 800000 | G16: Часть общих 3 млн ₽/год; разбивка по статьям — оценка
A17: ИИ-помощник и облачные модели | B17: ₽/год | C17: факт | D17: 700000 | E17: 700000 | F17: 700000 | G17: Часть общих 3 млн ₽/год; расход по журналу — app/rmr_*
A18: 3. Эффект: людей не нужно сажать на ручной учёт
A19: Объектов на одного человека ручного учёта | B19: объектов | C19: факт | D19: 3 | E19: 3 | F19: 3 | G19: Решение автора: один человек на 3 объекта (статусы поставки, численность, отчёты, привязка изделий)
A20: ФОТ одного человека с налогами и накладными | B20: ₽/год | C20: гипотеза | D20: 1800000 | E20: 1800000 | F20: 1800000 | G20: ≈150 тыс. ₽/мес.; заменить окладом вашей компании
A21: 4. Эффект: сокращение простоев и срывов поставки
A22: Объектов, где сервис ведёт учёт | B22: шт. | C22: факт | D22: 100 | E22: 100 | F22: 100 | G22: Решение автора: 100 объектов. Сегодня модель изделий загружена на 2 из 110 активных ЖБИ-объектов; эффект масштабируется числом объектов
A23: Срывов поставки на объект в год | B23: шт. | C23: гипотеза | D23: 1 | E23: 2 | F23: 3 | G23: По вашей статистике; без сервиса
A24: Дней простоя на один срыв | B24: дн. | C24: гипотеза | D24: 1 | E24: 1 | F24: 2
A25: Стоимость дня простоя площадки на объекте | B25: ₽/дн. | C25: факт | D25: 7000000 | E25: 7000000 | F25: 7000000 | G25: Оценка автора: ≈7 млн ₽ за день (поставка не вовремя или не в нужном порядке)
A26: Доля срывов, предотвращённых ранним видением | B26: % | C26: гипотеза | D26: 0.05 | E26: 0.1 | F26: 0.15 | G26: Аналитическая справка, комплектация под прогноз СМР
A27: 5. Эффект: меньше ошибок и переделок
A28: Изделий на объект в год | B28: шт. | C28: факт | D28: 7250 | E28: 7250 | F28: 7250 | G28: Факт: 14 507 изделий на 2 загруженных объектах ≈ 7 250 на объект
A29: Доля изделий с ошибкой учёта/привязки (без сервиса) | B29: % | C29: гипотеза | D29: 0.005 | E29: 0.01 | F29: 0.02 | G29: Неверная марка, адрес по осям, зона крана, двойной учёт
A30: Стоимость исправления одной ошибки | B30: ₽ | C30: гипотеза | D30: 5000 | E30: 8000 | F30: 12000 | G30: Перевозка/простой/пересогласование
A31: Доля ошибок, устраняемых сервисом | B31: % | C31: гипотеза | D31: 0.3 | E31: 0.5 | F31: 0.7 | G31: Привязка по DXF, проверки при загрузке, журнал
A32: 6. Эффект: контроль денег и сроков (ПП в деньгах)
A33: Годовой объём СМР под контролем ПП | B33: ₽/год | C33: гипотеза | D33: 500000000 | E33: 1000000000 | F33: 2000000000 | G33: Остаток денег по объектам из ПП; заменить цифрой из программы
A34: Доля объёма, где сдвиг сроков выявляется раньше | B34: % | C34: гипотеза | D34: 0.05 | E34: 0.1 | F34: 0.15
A35: На сколько дней раньше | B35: дн. | C35: гипотеза | D35: 5 | E35: 10 | F35: 15 | G35: Эффект — стоимость финансирования этих денег
